social_publisher
