Metadata-Version: 1.1
Name: django-social-publisher
Version: 0.5.4
Summary: Server-side content publishing extension for django-social-auth.
Home-page: https://github.com/scailer/django-social-publisher/
Author: Dmitriy Vlasov
Author-email: scailer@veles.biz
License: MIT license
Platform: UNKNOWN
Classifier: Framework :: Django
Classifier: Development Status :: 4 - Beta
Classifier: Environment :: Web Environment
Classifier: Intended Audience :: Developers
Classifier: License :: OSI Approved :: MIT License
Classifier: Programming Language :: Python
Classifier: Programming Language :: Python :: 2
Classifier: Programming Language :: Python :: 2.6
Classifier: Programming Language :: Python :: 2.7
Classifier: Programming Language :: Python :: 3
Classifier: Programming Language :: Python :: 3.4
Classifier: Programming Language :: Python :: 3.5
Classifier: Topic :: Software Development :: Libraries :: Python Modules
